{
  "meta": {
    "schemaVersion": "1.0",
    "sourceText": "-----test-----",
    "ingestionMethodId": 4,
    "contactId": 1021773,
    "observedAt": "2026-04-09T13:12:38Z"
  },
  "options": {
    "mode": "UPSERT",
    "dryRun": false,
    "createIfMissing": {
      "platform": true,
      "sensorSetups": true
    }
  },
  "platform": {
    "match": {
      "wigosId": null
    },
    "patch": {
      "name": "CPowerReefballs-EMOBON",
      "deployment": {
        "date": "2024-07-18T09:11:00Z",
        "latitude": 51.5806,
        "longitude": 2.9959
      },
      "retrieval": {
        "endDate": "2025-06-11T00:00:00Z"
      }
    }
  },
  "sensorSetups": [],
  "contactContributions": [],
  "agencyContributions": []
}